django_registrationwall-0.1.5.dist-info/DESCRIPTION.rst
django_registrationwall-0.1.5.dist-info/METADATA
django_registrationwall-0.1.5.dist-info/RECORD
django_registrationwall-0.1.5.dist-info/WHEEL
django_registrationwall-0.1.5.dist-info/metadata.json
django_registrationwall-0.1.5.dist-info/top_level.txt
regwall/__init__.py
regwall/mixins.py
regwall/settings.py
regwall/templates/.DS_Store
regwall/templates/regwall/detail.html
regwall/templates/regwall/history.html
regwall/templates/regwall/login.html
regwall/templatetags/__init__.py
regwall/templatetags/regwall_tags.py
regwall/tests/__init__.py
regwall/tests/settings.py
regwall/tests/urls.py
regwall/tests/articles/__init__.py
regwall/tests/articles/apps.py
regwall/tests/articles/models.py
regwall/tests/articles/urls.py
regwall/tests/articles/views.py
regwall/tests/articles/fixtures/articles_article.json
regwall/tests/articles/migrations/0001_initial.py
regwall/tests/articles/migrations/__init__.py
regwall/tests/templates/.DS_Store
regwall/tests/templates/base.html
regwall/tests/templates/articles/article_detail.html
regwall/tests/templates/registration/login.html
